fc_kc_bigdata.py
fc_big1-1.0.dist-info/METADATA
fc_big1-1.0.dist-info/WHEEL
fc_big1-1.0.dist-info/top_level.txt
fc_big1-1.0.dist-info/RECORD
