Metadata-Version: 2.1
Name: fc-big1
Version: 1.0
Summary: 大数据1
Home-page: UNKNOWN
Author: 大数据1
Author-email: fc@bigdata.com
License: UNKNOWN
Platform: UNKNOWN
